[
    {
      "code": 1,
      "rs": "Vadjenje zuba",
      "en": "Tooth extraction",
      "price": 20
    },
    {
      "code": 2,
      "rs": "Komplikovano vadjenje zuba",
      "en": "Complicated tooth extraction",
      "price": 40
    },
    {
      "code": 3,
      "rs": "Ukl.kamenca ultr.",
      "en": "Removal of soft and hard plaque with polishing (teeth cleaning)",
      "price": 30
    },
    {
      "code": 4,
      "rs": "Polir.peskarenje",
      "en": "Polishing and sandblasting",
      "price": 20
    },
    {
      "code": 5,
      "rs": "Obr.parad.dzepa",
      "en": "Periodontal pocket treatment",
      "price": 20
    },
    {
      "code": 6,
      "rs": "Helbo laser",
      "en": "Helbo laser (both jaw)",
      "price": 210
    },
    {
      "code": 7,
      "rs": "Frenulum",
      "en": "Frenectomy (lip ligament removal)",
      "price": 100
    },
    {
      "code": 8,
      "rs": "Kompozirtni ispun",
      "en": "Composite filling on 1 or 2 surfaces",
      "price": 25
    },
    {
      "code": 9,
      "rs": "Kompozirtni ispun m.o.d",
      "en": "Composite filling on 3 surfaces",
      "price": 30
    },
    {
      "code": 10,
      "rs": "Kompozitna rekonstrukcija",
      "en": "Composite reconstruction",
      "price": 40
    },
    {
      "code": 11,
      "rs": "Vitalna ili mortalna ekstirpacija",
      "en": "Vital or gangrenous expiration",
      "price": 20
    },
    {
      "code": 12,
      "rs": "Lokalna aplikacija leka",
      "en": "Local medicament application (root canal)",
      "price": 10
    },
    {
      "code": 13,
      "rs": "Okluzalni splint",
      "en": "Retention splint",
      "price": 70
    },
    {
      "code": 14,
      "rs": "Metalo-keramicka kruna",
      "en": "Metal ceramic crown (temporary)",
      "price": 110
    },
    {
      "code": 15,
      "rs": "Bezmetalna keramicka kruna I",
      "en": "Ceramic crown I (zirconium)",
      "price": 300
    },
    {
      "code": 16,
      "rs": "Bezmetalna keramicka kruna II",
      "en": "Ceramic crown II (zirconium)",
      "price": 250
    },
    {
      "code": 17,
      "rs": "Fiber kocic sa nadogradnjom",
      "en": "Fiberglass peg (composite reconstruction)",
      "price": 70
    },
    {
      "code": 18,
      "rs": "parcijalna plocasta proteza",
      "en": "Partial acrylic denture per jaw",
      "price": 200
    },
    {
      "code": 19,
      "rs": "Totalna plocasta proteza",
      "en": "Total acrylic denture per jaw",
      "price": 200
    },
    {
      "code": 20,
      "rs": "Skeletirana proteza",
      "en": "Metal- based denture per jaw",
      "price": 350
    },
    {
      "code": 21,
      "rs": "Atecmeni",
      "en": "Attachments",
      "price": 30
    },
    {
      "code": 22,
      "rs": "Defleks proteza",
      "en": "Silicone denture",
      "price": 350
    },
    {
      "code": 23,
      "rs": "Repatura polomljene proteze",
      "en": "Reparation of denture",
      "price": 30
    },
    {
      "code": 24,
      "rs": "Podlaganje proteze",
      "en": "Denture relining",
      "price": 60
    },
    {
      "code": 25,
      "rs": "Lasersko beljenje zuba",
      "en": "Laser Teeth whitening",
      "price": 200
    },
    {
      "code": 26,
      "rs": "Kucno beljenje zuba",
      "en": "Home teeth whitening",
      "price": 200
    },
    {
      "code": 27,
      "rs": "Kompozitna faseta",
      "en": "Direct composite veneer",
      "price": 50
    },
    {
      "code": 28,
      "rs": "Uklanjanje mekih naslaga",
      "en": "Teeth cleaning (soft plaque)",
      "price": 10
    },
    {
      "code": 29,
      "rs": "Vadjenje mlecnog zuba",
      "en": "Milk teeth extraction",
      "price": 10
    },
    {
      "code": 30,
      "rs": "Fiksa proteza metalna",
      "en": "Fixed unit with conventional metal brackets, per jaw",
      "price": 600
    },
        {
      "code": 31,
      "rs": "Fiksna proteza estetska",
      "en": "Fixed unit with covnetional aesthetic brackets, per jaw",
      "price": 800
    },
    {
      "code": 32,
      "rs": "Mobilna decija proteza",
      "en": "Active mobile unit per jaw",
      "price": 600
    },
    {
      "code": 33,
      "rs": "Tvins blok decija proteza",
      "en": "Twin block appliance",
      "price": 600
    },
    {
      "code": 34,
      "rs": "Zalivanje fisura",
      "en": "Fissure sealing",
      "price": 15
    },
    {
      "code": 35,
      "rs": "Lokalna aplikacija leka",
      "en": "Local medicament aplication",
      "price": 20
    },
    {
      "code": 36,
      "rs": "Kompozitni ispun ml.zuba",
      "en": "Composite filling milk teeth",
      "price": 15
    },
    {
      "code": 37,
      "rs": "Zubni nakit",
      "en": "Dental jewelry",
      "price": 40
    },
    {
      "code": 38,
      "rs": "Strauman implant",
      "en": "Straumann implant",
      "price": 700
    },
    {
      "code": 39,
      "rs": "Bredent implant",
      "en": "Bredent implant",
      "price": 600
    },
    {
      "code": 40,
      "rs": "Mis implant",
      "en": "Mis implant",
      "price": 600
    },
    {
      "code": 41,
      "rs": "Metalokeramicka kruna implant",
      "en": "Metal ceramic crown on implant",
      "price": 250
    },
    {
      "code": 42,
      "rs": "Bezmetalna kruna implant",
      "en": "Ceramic crown on implant",
      "price": 350
    },
    {
      "code": 43,
      "rs": "Keramicki viniri",
      "en": "Ceramic veneer",
      "price": 350
    },
    {
      "code": 44,
      "rs": "Skeletirana proteza na precki",
      "en": "Metal based denture on bar(implant system)",
      "price": 2400
    },
    {
      "code": 45,
      "rs": "Skeletirana proteza bio hpp 4imp",
      "en": "Metal based denture BioHpp on implants",
      "price": 3000
    },
    {
      "code": 46,
      "rs": "Fiksni rad na sraf biohpp cirkon",
      "en": "Temporary crowns on implants Screw-BioHpp-Zirconium",
      "price": 4000
    },
    {
      "code": 47,
      "rs": "Fiksni rad na sraf cirkon biohpp cirkon",
      "en": "Temporary crowns on implants Screw-Zirconium-BioHpp-Zirconium",
      "price": 3500
    },
    {
      "code": 48,
      "rs": "Skeletirana proteza 2 lokatora",
      "en": "Metal based denture with 2 locator abutments on implant",
      "price": 1400
    },
    {
      "code": 49,
      "rs": "Biohpp proteza 2 lokatora",
      "en": "BioHpp denture( 2 locator abutments on implant)",
      "price": 2000
    },
    {
      "code": 50,
      "rs": "MWRO operacija po zubu",
      "en": "MWF surgery per tooth",
      "price": 50
    },
    {
      "code": 51,
      "rs": "Kostani zamenik BIo-oss",
      "en": "Bone substitute material BioOss",
      "price": 180
    },
    {
      "code": 52,
      "rs": "Augmentaciona procedura",
      "en": "Augmentation procedure",
      "price": 100
    },
    {
      "code": 53,
      "rs": "Kolagena membrana",
      "en": "Collagen membrane",
      "price": 300
    },
    {
      "code": 54,
      "rs": "Produbljivanje forniksa",
      "en": "Fornix reshaping",
      "price": 150
    },
    {
      "code": 55,
      "rs": "Nivelacija grebena",
      "en": "Alveolar ridge leveling",
      "price": 150
    },
    {
      "code": 56,
      "rs": "Hirusko vadjenje zuba",
      "en": "Surgical extraction of impacted tooth",
      "price": 150
    },
    {
      "code": 57,
      "rs": "Resekcija vrha korena",
      "en": "Apicoectomy",
      "price": 150
    },
    {
        "code": 58,
        "rs": "Sinus floor elevation + material",
        "en": "Sinus floor elevation + material",
        "price": 800
      },
      {
        "code": 59,
        "rs": "All on 4 implant system (metal ceramic crown)",
        "en": "All on 4 implant system (metal ceramic crown)",
        "price": 4500
      },
      {
        "code": 60,
        "rs": "All on 6 implant system (metal ceramic crown)",
        "en": "All on 6 implant system (metal ceramic crown)",
        "price": 6500
      },
      {
        "code": 61,
        "rs": "Cystetomy",
        "en": "Cystetomy",
        "price": 200
      }

]